hello.py
helloworld_mj-0.0.1.dist-info/METADATA
helloworld_mj-0.0.1.dist-info/WHEEL
helloworld_mj-0.0.1.dist-info/top_level.txt
helloworld_mj-0.0.1.dist-info/RECORD
